tno/quantum/optimization/qubo/postprocessors/__init__.py
tno/quantum/optimization/qubo/postprocessors/py.typed
tno/quantum/optimization/qubo/postprocessors/_dwave/_steepest_descent_postprocessor.py
tno/quantum/optimization/qubo/postprocessors/test/__init__.py
tno/quantum/optimization/qubo/postprocessors/test/test_steepest_descent_postprocessor.py
tno_quantum_optimization_qubo_postprocessors-1.0.0.dist-info/licenses/LICENSE
tno_quantum_optimization_qubo_postprocessors-1.0.0.dist-info/METADATA
tno_quantum_optimization_qubo_postprocessors-1.0.0.dist-info/WHEEL
tno_quantum_optimization_qubo_postprocessors-1.0.0.dist-info/top_level.txt
tno_quantum_optimization_qubo_postprocessors-1.0.0.dist-info/RECORD
